kubiya/__init__.py
kubiya/__version__.py
kubiya/cli.py
kubiya/client.py
kubiya/execution.py
kubiya/py.typed
kubiya/core/__init__.py
kubiya/core/constants.py
kubiya/core/exceptions.py
kubiya/core/sentry_config.py
kubiya/core/serialization.py
kubiya/core/types.py
kubiya/core/models/__init__.py
kubiya/core/models/cli/__init__.py
kubiya/core/models/cli/models.py
kubiya/core/models/server/__init__.py
kubiya/core/models/server/requests.py
kubiya/core/stream/__init__.py
kubiya/core/stream/manager.py
kubiya/dsl/__init__.py
kubiya/dsl/control_flow.py
kubiya/dsl/data.py
kubiya/dsl/examples.py
kubiya/dsl/executors.py
kubiya/dsl/lifecycle.py
kubiya/dsl/queue.py
kubiya/dsl/scheduling.py
kubiya/dsl/step.py
kubiya/dsl/workflow.py
kubiya/dsl_experimental/__init__.py
kubiya/dsl_experimental/control_flow.py
kubiya/dsl_experimental/data.py
kubiya/dsl_experimental/examples.py
kubiya/dsl_experimental/executors.py
kubiya/dsl_experimental/lifecycle.py
kubiya/dsl_experimental/scheduling.py
kubiya/dsl_experimental/step.py
kubiya/dsl_experimental/workflow.py
kubiya/kubiya_cli/bundle/__init__.py
kubiya/kubiya_cli/bundle/bundler.py
kubiya/kubiya_cli/init_command_folder/tools/__init__.py
kubiya/kubiya_cli/init_command_folder/tools/function_tool/main.py
kubiya/kubiya_cli/init_command_folder/tools/hello_world_tool/__init__.py
kubiya/kubiya_cli/init_command_folder/tools/hello_world_tool/main.py
kubiya/kubiya_cli/init_command_folder/tools/hello_world_tool/tool_def.py
kubiya/mcp/__init__.py
kubiya/mcp/agent_server.py
kubiya/mcp/client.py
kubiya/mcp/interactive_chat.py
kubiya/mcp/server.py
kubiya/mcp/test_agent.py
kubiya/mcp/test_client.py
kubiya/mcp/server/__init__.py
kubiya/mcp/server/__main__.py
kubiya/mcp/server/context.py
kubiya/mcp/server/core.py
kubiya/mcp/server/prompts.py
kubiya/mcp/server/resources.py
kubiya/mcp/server/tools.py
kubiya/resources/__init__.py
kubiya/resources/constants.py
kubiya/resources/exceptions.py
kubiya/resources/utils.py
kubiya/resources/services/__init__.py
kubiya_sdk-2.0.4.dist-info/licenses/LICENSE
kubiya_sdk-2.0.4.dist-info/METADATA
kubiya_sdk-2.0.4.dist-info/WHEEL
kubiya_sdk-2.0.4.dist-info/entry_points.txt
kubiya_sdk-2.0.4.dist-info/top_level.txt
kubiya_sdk-2.0.4.dist-info/RECORD
