Metadata-Version: 2.4
Name: kubiya-sdk
Version: 2.0.4
Summary: SDK for building and managing Kubiya workflows
Author-email: Kubiya Team <support@kubiya.ai>
License: AGPL-3.0
Project-URL: Homepage, https://github.com/kubiyabot/workflow_sdk
Project-URL: Documentation, https://docs.kubiya.ai/workflow_sdk
Project-URL: Repository, https://github.com/kubiyabot/workflow_sdk
Project-URL: Issues, https://github.com/kubiyabot/workflow_sdk/issues
Keywords: kubiya,workflow,sdk,automation,ai
Classifier: Development Status :: 4 - Beta
Classifier: Intended Audience :: Developers
Classifier: License :: OSI Approved :: GNU Affero General Public License v3 or later (AGPLv3+)
Classifier: Operating System :: OS Independent
Classifier: Programming Language :: Python :: 3
Classifier: Programming Language :: Python :: 3.9
Classifier: Programming Language :: Python :: 3.10
Classifier: Programming Language :: Python :: 3.11
Classifier: Programming Language :: Python :: 3.12
Classifier: Programming Language :: Python :: 3.13
Classifier: Topic :: Software Development :: Libraries :: Python Modules
Classifier: Topic :: System :: Distributed Computing
Requires-Python: <4.0,>=3.10
License-File: LICENSE
Requires-Dist: pydantic>=2.0.0
Requires-Dist: httpx>=0.24.0
Requires-Dist: aiohttp>=3.8.0
Requires-Dist: python-dotenv>=1.0.0
Requires-Dist: click>=8.0.0
Requires-Dist: rich>=13.0.0
Requires-Dist: PyYAML>=6.0
Requires-Dist: requests>=2.25.0
Requires-Dist: multipledispatch>=1.0.0
Provides-Extra: dev
Requires-Dist: black>=23.0.0; extra == "dev"
Requires-Dist: ruff>=0.1.0; extra == "dev"
Requires-Dist: mypy>=1.0.0; extra == "dev"
Requires-Dist: pre-commit>=3.0.0; extra == "dev"
Provides-Extra: mcp
Requires-Dist: fastmcp>=1.1.4; extra == "mcp"
Requires-Dist: mcp>=1.1.3; extra == "mcp"
Requires-Dist: pyee>=12.1.1; extra == "mcp"
Requires-Dist: fastapi>=0.115; extra == "mcp"
Requires-Dist: sse_starlette>=2.3; extra == "mcp"
Requires-Dist: aiofiles>=24.1; extra == "mcp"
Provides-Extra: auth
Requires-Dist: mcpauth>=0.1.0; extra == "auth"
Requires-Dist: starlette>=0.46.0; extra == "auth"
Requires-Dist: uvicorn>=0.30.0; extra == "auth"
Provides-Extra: sentry
Requires-Dist: sentry-sdk>=2.0.0; extra == "sentry"
Provides-Extra: stream
Requires-Dist: nats-py>=2.9.0; extra == "stream"
Provides-Extra: server
Requires-Dist: fastapi>=0.115; extra == "server"
Requires-Dist: uvicorn>=0.30.0; extra == "server"
Requires-Dist: sse_starlette>=2.3; extra == "server"
Requires-Dist: multipledispatch>=1.0.0; extra == "server"
Requires-Dist: sentry-sdk>=2.0.0; extra == "server"
Requires-Dist: jmespath>=1.0.1; extra == "server"
Provides-Extra: all
Requires-Dist: fastmcp>=1.1.4; extra == "all"
Requires-Dist: mcp>=1.1.3; extra == "all"
Requires-Dist: pyee>=12.1.1; extra == "all"
Requires-Dist: fastapi>=0.115; extra == "all"
Requires-Dist: sse_starlette>=2.3; extra == "all"
Requires-Dist: aiofiles>=24.1; extra == "all"
Requires-Dist: mcpauth>=0.1.0; extra == "all"
Requires-Dist: starlette>=0.46.0; extra == "all"
Requires-Dist: uvicorn>=0.30.0; extra == "all"
Requires-Dist: sentry-sdk>=2.0.0; extra == "all"
Requires-Dist: multipledispatch>=1.0.0; extra == "all"
Requires-Dist: pytest>=7.0.0; extra == "all"
Requires-Dist: pytest-cov>=4.0.0; extra == "all"
Requires-Dist: pytest-asyncio>=0.21.0; extra == "all"
Requires-Dist: black>=23.0.0; extra == "all"
Requires-Dist: ruff>=0.1.0; extra == "all"
Requires-Dist: mypy>=1.0.0; extra == "all"
Requires-Dist: pre-commit>=3.0.0; extra == "all"
Requires-Dist: nats-py>=2.9.0; extra == "all"
Requires-Dist: jmespath>=1.0.1; extra == "all"
Requires-Dist: typer>=0.12.5; extra == "all"
Dynamic: license-file
